pickpock/__init__.py
pickpock-0.1.5.dist-info/METADATA
pickpock-0.1.5.dist-info/WHEEL
pickpock-0.1.5.dist-info/RECORD
