Metadata-Version: 2.1
Name: pickpock
Version: 0.1.5
Summary: A re-implementation of Deen Freelon's pyktok
Author: Pascal Jürgens
Author-email: juergens@uni-trier.de
Requires-Python: >=3.9,<4.0
Classifier: License :: OSI Approved :: MIT License
Classifier: Operating System :: OS Independent
Classifier: Programming Language :: Python :: 3
Classifier: Programming Language :: Python :: 3.9
Classifier: Programming Language :: Python :: 3.10
Classifier: Programming Language :: Python :: 3.11
Requires-Dist: browser-cookie3 (>=0.19.1,<0.20.0)
Requires-Dist: requests (>=2.31.0,<3.0.0)
Requires-Dist: selectolax (>=0.3.17,<0.4.0)
